frontend/__init__.py
frontend/algorithms/__init__.py
frontend/algorithms/elaborateAssignment.py
frontend/algorithms/exportDOT.py
frontend/algorithms/extractARG.py
frontend/algorithms/extractCIP.py
frontend/algorithms/extractFSM.py
frontend/algorithms/extractGraph.py
frontend/algorithms/extractREG.py
frontend/algorithms/highlight.py
frontend/algorithms/run.sh
frontend/modules/__init__.py
frontend/modules/definitions.py
frontend/modules/module.py
frontend/modules/netlist.py
frontend/modules/ports.py
frontend/modules/statement.py
frontend/modules/dfg/__init__.py
frontend/modules/dfg/graph.py
frontend/modules/dfg/node.py
frontend/reader/__init__.py
frontend/reader/verilogReader/__init__.py
frontend/reader/verilogReader/conditionTransformer.py
frontend/reader/verilogReader/expressionTransformer.py
frontend/reader/verilogReader/grammar_systemverilog.lark
frontend/reader/verilogReader/moduleTransformer.py
frontend/reader/verilogReader/portTransformer.py
frontend/reader/verilogReader/reader.py
frontend/reader/verilogReader/verilogTransformer.py
frontend/writer/__init__.py
frontend/writer/verilogWriter/__init__.py
frontend/writer/verilogWriter/headerWriter.py
frontend/writer/verilogWriter/moduleWriter.py
frontend/writer/verilogWriter/writer.py
leap_frontend-0.1.4.dist-info/LICENSE
leap_frontend-0.1.4.dist-info/METADATA
leap_frontend-0.1.4.dist-info/WHEEL
leap_frontend-0.1.4.dist-info/top_level.txt
leap_frontend-0.1.4.dist-info/RECORD
