Metadata-Version: 2.1
Name: leap-frontend
Version: 0.1.4
Summary: The frontend of the LEAP framework
Author: Hanyu Wang
License: MIT License
Project-URL: Documentation, https://leap-frontend.readthedocs.io/en/latest/
Project-URL: Repository, https://github.com/Nozidoali/leap-frontend
Keywords: high-level synthesis,verilog,system verilog
Classifier: Programming Language :: Python :: 3
Classifier: Operating System :: OS Independent
Requires-Python: >=3.11
License-File: LICENSE
Requires-Dist: lark>=1.2
Requires-Dist: pygraphviz>=1.10
